alphatriangle/__init__.py
alphatriangle/cli.py
alphatriangle/config/README.md
alphatriangle/config/__init__.py
alphatriangle/config/app_config.py
alphatriangle/config/env_config.py
alphatriangle/config/mcts_config.py
alphatriangle/config/model_config.py
alphatriangle/config/persistence_config.py
alphatriangle/config/train_config.py
alphatriangle/config/validation.py
alphatriangle/data/README.md
alphatriangle/data/__init__.py
alphatriangle/data/data_manager.py
alphatriangle/data/path_manager.py
alphatriangle/data/schemas.py
alphatriangle/data/serializer.py
alphatriangle/features/README.md
alphatriangle/features/__init__.py
alphatriangle/features/extractor.py
alphatriangle/features/grid_features.py
alphatriangle/mcts/README.md
alphatriangle/mcts/__init__.py
alphatriangle/mcts/core/README.md
alphatriangle/mcts/core/__init__.py
alphatriangle/mcts/core/node.py
alphatriangle/mcts/core/search.py
alphatriangle/mcts/core/types.py
alphatriangle/mcts/strategy/README.md
alphatriangle/mcts/strategy/__init__.py
alphatriangle/mcts/strategy/backpropagation.py
alphatriangle/mcts/strategy/expansion.py
alphatriangle/mcts/strategy/policy.py
alphatriangle/mcts/strategy/selection.py
alphatriangle/nn/README.md
alphatriangle/nn/__init__.py
alphatriangle/nn/model.py
alphatriangle/nn/network.py
alphatriangle/rl/README.md
alphatriangle/rl/__init__.py
alphatriangle/rl/types.py
alphatriangle/rl/core/README.md
alphatriangle/rl/core/__init__.py
alphatriangle/rl/core/buffer.py
alphatriangle/rl/core/trainer.py
alphatriangle/rl/self_play/README.md
alphatriangle/rl/self_play/__init__.py
alphatriangle/rl/self_play/worker.py
alphatriangle/stats/README.md
alphatriangle/stats/__init__.py
alphatriangle/stats/collector.py
alphatriangle/training/README.md
alphatriangle/training/__init__.py
alphatriangle/training/components.py
alphatriangle/training/logging_utils.py
alphatriangle/training/loop.py
alphatriangle/training/loop_helpers.py
alphatriangle/training/runner.py
alphatriangle/training/runners.py
alphatriangle-1.0.0.dist-info/licenses/LICENSE
alphatriangle-1.0.0.dist-info/METADATA
alphatriangle-1.0.0.dist-info/WHEEL
alphatriangle-1.0.0.dist-info/entry_points.txt
alphatriangle-1.0.0.dist-info/top_level.txt
alphatriangle-1.0.0.dist-info/RECORD
