Metadata-Version: 2.4
Name: alphatriangle
Version: 1.0.0
Summary: AlphaZero implementation for a triangle puzzle game (uses trianglengin).
Author-email: "Luis Guilherme P. M." <lgpelin92@gmail.com>
License: MIT License
Project-URL: Homepage, https://github.com/lguibr/alphatriangle
Project-URL: Bug Tracker, https://github.com/lguibr/alphatriangle/issues
Classifier: Programming Language :: Python :: 3
Classifier: Programming Language :: Python :: 3.10
Classifier: Programming Language :: Python :: 3.11
Classifier: License :: OSI Approved :: MIT License
Classifier: Operating System :: OS Independent
Classifier: Topic :: Scientific/Engineering :: Artificial Intelligence
Classifier: Topic :: Games/Entertainment :: Puzzle Games
Classifier: Development Status :: 4 - Beta
Requires-Python: >=3.10
License-File: LICENSE
Requires-Dist: trianglengin>=1.0.6
Requires-Dist: numpy>=1.20.0
Requires-Dist: torch>=2.0.0
Requires-Dist: torchvision>=0.11.0
Requires-Dist: cloudpickle>=2.0.0
Requires-Dist: numba>=0.55.0
Requires-Dist: mlflow>=1.20.0
Requires-Dist: ray>=2.8.0
Requires-Dist: pydantic>=2.0.0
Requires-Dist: typing_extensions>=4.0.0
Requires-Dist: typer[all]>=0.9.0
Requires-Dist: tensorboard>=2.10.0
Provides-Extra: dev
Requires-Dist: pytest>=7.0.0; extra == "dev"
Requires-Dist: pytest-cov>=3.0.0; extra == "dev"
Requires-Dist: pytest-mock>=3.0.0; extra == "dev"
Requires-Dist: ruff; extra == "dev"
Requires-Dist: mypy; extra == "dev"
Requires-Dist: build; extra == "dev"
Requires-Dist: twine; extra == "dev"
Requires-Dist: codecov; extra == "dev"
Dynamic: license-file
